multipolynomial_bases/__init__.py
multipolynomial_bases/ambient_space_basis.py
multipolynomial_bases/bases.py
multipolynomial_bases/basis.py
multipolynomial_bases/double_multivariate_polynomials.py
multipolynomial_bases/linear_basis_on_vectors.py
multipolynomial_bases/monomial.py
multipolynomial_bases/multivariate_polynomials.py
multipolynomial_bases-2.1.dist-info/LICENSE
multipolynomial_bases-2.1.dist-info/METADATA
multipolynomial_bases-2.1.dist-info/WHEEL
multipolynomial_bases-2.1.dist-info/top_level.txt
multipolynomial_bases-2.1.dist-info/RECORD
