Metadata-Version: 2.1
Name: multipolynomial-bases
Version: 2.1
Summary: Sage implementation for bases of multipolynomials
Home-page: https://github.com/VivianePons/multipolynomial-bases
Author: Viviane Pons
Author-email: viviane.pons@lri.fr
License: GPLv2
Keywords: SageMath Schubert Grothendieck polynomials
Platform: UNKNOWN
Classifier: Development Status :: 4 - Beta
Classifier: Intended Audience :: Science/Research
Classifier: Topic :: Software Development :: Build Tools
Classifier: Topic :: Scientific/Engineering :: Mathematics
Classifier: License :: OSI Approved :: GNU General Public License v2 or later (GPLv2+)
Classifier: Programming Language :: Python :: 3.7
